bcd.v
module bcdflow(X,Y,Output);
    input [3:0]X;
    input [3:0]Y;
    output [3:0]Output;
    wire [3:0]out;
    assign out = X + Y;
    assign Output = (out > 4'b1001)? (out + 4'b0110):out;
endmodule

bcdflow_sim.v
`include "bcd.v"
module simulation();
    integer i = 0, j = 0;
    reg [3:0]A,B;
    wire [3:0]out;
    bcdflow uut(A,B,out);
    initial begin 
        $dumpfile ("flowWave.vcd");
        $dumpvars (0,simulation);
        for (i = 0; i<16 ; i = i + 1)
        begin
            A = i;
            for (j = 0; j<16; j = j + 1)
            begin
                B =j;
                #10;
            end
        end
    end
endmodule

flowWave.vcd
$date
	Thu Oct 20 11:27:08 2022
$end
$version
	Icarus Verilog
$end
$timescale
	1s
$end
$scope module simulation $end
$var wire 4 ! out [3:0] $end
$var reg 4 " A [3:0] $end
$var reg 4 # B [3:0] $end
$var integer 32 $ i [31:0] $end
$var integer 32 % j [31:0] $end
$scope module uut $end
$var wire 4 & X [3:0] $end
$var wire 4 ' Y [3:0] $end
$var wire 4 ( out [3:0] $end
$var wire 4 ) Output [3:0] $end
$upscope $end
$upscope $end
$enddefinitions $end
#0
$dumpvars
b0 )
b0 (
b0 '
b0 &
b0 %
b0 $
b0 #
b0 "
b0 !
$end
#10
b1 !
b1 )
b1 (
b1 #
b1 '
b1 %
#20
b10 !
b10 )
b10 (
b10 #
b10 '
b10 %
#30
b11 !
b11 )
b11 (
b11 #
b11 '
b11 %
#40
b100 !
b100 )
b100 (
b100 #
b100 '
b100 %
#50
b101 !
b101 )
b101 (
b101 #
b101 '
b101 %
#60
b110 !
b110 )
b110 (
b110 #
b110 '
b110 %
#70
b111 !
b111 )
b111 (
b111 #
b111 '
b111 %
#80
b1000 !
b1000 )
b1000 (
b1000 #
b1000 '
b1000 %
#90
b1001 !
b1001 )
b1001 (
b1001 #
b1001 '
b1001 %
#100
b0 !
b0 )
b1010 (
b1010 #
b1010 '
b1010 %
#110
b1 !
b1 )
b1011 (
b1011 #
b1011 '
b1011 %
#120
b10 !
b10 )
b1100 (
b1100 #
b1100 '
b1100 %
#130
b11 !
b11 )
b1101 (
b1101 #
b1101 '
b1101 %
#140
b100 !
b100 )
b1110 (
b1110 #
b1110 '
b1110 %
#150
b101 !
b101 )
b1111 (
b1111 #
b1111 '
b1111 %
#160
b1 !
b1 )
b0 #
b0 '
b1 (
b1 "
b1 &
b1 $
b0 %
#170
b10 !
b10 )
b10 (
b1 #
b1 '
b1 %
#180
b11 !
b11 )
b11 (
b10 #
b10 '
b10 %
#190
b100 !
b100 )
b100 (
b11 #
b11 '
b11 %
#200
b101 !
b101 )
b101 (
b100 #
b100 '
b100 %
#210
b110 !
b110 )
b110 (
b101 #
b101 '
b101 %
#220
b111 !
b111 )
b111 (
b110 #
b110 '
b110 %
#230
b1000 !
b1000 )
b1000 (
b111 #
b111 '
b111 %
#240
b1001 !
b1001 )
b1001 (
b1000 #
b1000 '
b1000 %
#250
b0 !
b0 )
b1010 (
b1001 #
b1001 '
b1001 %
#260
b1 !
b1 )
b1011 (
b1010 #
b1010 '
b1010 %
#270
b10 !
b10 )
b1100 (
b1011 #
b1011 '
b1011 %
#280
b11 !
b11 )
b1101 (
b1100 #
b1100 '
b1100 %
#290
b100 !
b100 )
b1110 (
b1101 #
b1101 '
b1101 %
#300
b101 !
b101 )
b1111 (
b1110 #
b1110 '
b1110 %
#310
b0 !
b0 )
b0 (
b1111 #
b1111 '
b1111 %
#320
b10 !
b10 )
b0 #
b0 '
b10 (
b10 "
b10 &
b10 $
b0 %
#330
b11 !
b11 )
b11 (
b1 #
b1 '
b1 %
#340
b100 !
b100 )
b100 (
b10 #
b10 '
b10 %
#350
b101 !
b101 )
b101 (
b11 #
b11 '
b11 %
#360
b110 !
b110 )
b110 (
b100 #
b100 '
b100 %
#370
b111 !
b111 )
b111 (
b101 #
b101 '
b101 %
#380
b1000 !
b1000 )
b1000 (
b110 #
b110 '
b110 %
#390
b1001 !
b1001 )
b1001 (
b111 #
b111 '
b111 %
#400
b0 !
b0 )
b1010 (
b1000 #
b1000 '
b1000 %
#410
b1 !
b1 )
b1011 (
b1001 #
b1001 '
b1001 %
#420
b10 !
b10 )
b1100 (
b1010 #
b1010 '
b1010 %
#430
b11 !
b11 )
b1101 (
b1011 #
b1011 '
b1011 %
#440
b100 !
b100 )
b1110 (
b1100 #
b1100 '
b1100 %
#450
b101 !
b101 )
b1111 (
b1101 #
b1101 '
b1101 %
#460
b0 !
b0 )
b0 (
b1110 #
b1110 '
b1110 %
#470
b1 !
b1 )
b1 (
b1111 #
b1111 '
b1111 %
#480
b11 !
b11 )
b0 #
b0 '
b11 (
b11 "
b11 &
b11 $
b0 %
#490
b100 !
b100 )
b100 (
b1 #
b1 '
b1 %
#500
b101 !
b101 )
b101 (
b10 #
b10 '
b10 %
#510
b110 !
b110 )
b110 (
b11 #
b11 '
b11 %
#520
b111 !
b111 )
b111 (
b100 #
b100 '
b100 %
#530
b1000 !
b1000 )
b1000 (
b101 #
b101 '
b101 %
#540
b1001 !
b1001 )
b1001 (
b110 #
b110 '
b110 %
#550
b0 !
b0 )
b1010 (
b111 #
b111 '
b111 %
#560
b1 !
b1 )
b1011 (
b1000 #
b1000 '
b1000 %
#570
b10 !
b10 )
b1100 (
b1001 #
b1001 '
b1001 %
#580
b11 !
b11 )
b1101 (
b1010 #
b1010 '
b1010 %
#590
b100 !
b100 )
b1110 (
b1011 #
b1011 '
b1011 %
#600
b101 !
b101 )
b1111 (
b1100 #
b1100 '
b1100 %
#610
b0 !
b0 )
b0 (
b1101 #
b1101 '
b1101 %
#620
b1 !
b1 )
b1 (
b1110 #
b1110 '
b1110 %
#630
b10 !
b10 )
b10 (
b1111 #
b1111 '
b1111 %
#640
b100 !
b100 )
b0 #
b0 '
b100 (
b100 "
b100 &
b100 $
b0 %
#650
b101 !
b101 )
b101 (
b1 #
b1 '
b1 %
#660
b110 !
b110 )
b110 (
b10 #
b10 '
b10 %
#670
b111 !
b111 )
b111 (
b11 #
b11 '
b11 %
#680
b1000 !
b1000 )
b1000 (
b100 #
b100 '
b100 %
#690
b1001 !
b1001 )
b1001 (
b101 #
b101 '
b101 %
#700
b0 !
b0 )
b1010 (
b110 #
b110 '
b110 %
#710
b1 !
b1 )
b1011 (
b111 #
b111 '
b111 %
#720
b10 !
b10 )
b1100 (
b1000 #
b1000 '
b1000 %
#730
b11 !
b11 )
b1101 (
b1001 #
b1001 '
b1001 %
#740
b100 !
b100 )
b1110 (
b1010 #
b1010 '
b1010 %
#750
b101 !
b101 )
b1111 (
b1011 #
b1011 '
b1011 %
#760
b0 !
b0 )
b0 (
b1100 #
b1100 '
b1100 %
#770
b1 !
b1 )
b1 (
b1101 #
b1101 '
b1101 %
#780
b10 !
b10 )
b10 (
b1110 #
b1110 '
b1110 %
#790
b11 !
b11 )
b11 (
b1111 #
b1111 '
b1111 %
#800
b101 !
b101 )
b0 #
b0 '
b101 (
b101 "
b101 &
b101 $
b0 %
#810
b110 !
b110 )
b110 (
b1 #
b1 '
b1 %
#820
b111 !
b111 )
b111 (
b10 #
b10 '
b10 %
#830
b1000 !
b1000 )
b1000 (
b11 #
b11 '
b11 %
#840
b1001 !
b1001 )
b1001 (
b100 #
b100 '
b100 %
#850
b0 !
b0 )
b1010 (
b101 #
b101 '
b101 %
#860
b1 !
b1 )
b1011 (
b110 #
b110 '
b110 %
#870
b10 !
b10 )
b1100 (
b111 #
b111 '
b111 %
#880
b11 !
b11 )
b1101 (
b1000 #
b1000 '
b1000 %
#890
b100 !
b100 )
b1110 (
b1001 #
b1001 '
b1001 %
#900
b101 !
b101 )
b1111 (
b1010 #
b1010 '
b1010 %
#910
b0 !
b0 )
b0 (
b1011 #
b1011 '
b1011 %
#920
b1 !
b1 )
b1 (
b1100 #
b1100 '
b1100 %
#930
b10 !
b10 )
b10 (
b1101 #
b1101 '
b1101 %
#940
b11 !
b11 )
b11 (
b1110 #
b1110 '
b1110 %
#950
b100 !
b100 )
b100 (
b1111 #
b1111 '
b1111 %
#960
b110 !
b110 )
b0 #
b0 '
b110 (
b110 "
b110 &
b110 $
b0 %
#970
b111 !
b111 )
b111 (
b1 #
b1 '
b1 %
#980
b1000 !
b1000 )
b1000 (
b10 #
b10 '
b10 %
#990
b1001 !
b1001 )
b1001 (
b11 #
b11 '
b11 %
#1000
b0 !
b0 )
b1010 (
b100 #
b100 '
b100 %
#1010
b1 !
b1 )
b1011 (
b101 #
b101 '
b101 %
#1020
b10 !
b10 )
b1100 (
b110 #
b110 '
b110 %
#1030
b11 !
b11 )
b1101 (
b111 #
b111 '
b111 %
#1040
b100 !
b100 )
b1110 (
b1000 #
b1000 '
b1000 %
#1050
b101 !
b101 )
b1111 (
b1001 #
b1001 '
b1001 %
#1060
b0 !
b0 )
b0 (
b1010 #
b1010 '
b1010 %
#1070
b1 !
b1 )
b1 (
b1011 #
b1011 '
b1011 %
#1080
b10 !
b10 )
b10 (
b1100 #
b1100 '
b1100 %
#1090
b11 !
b11 )
b11 (
b1101 #
b1101 '
b1101 %
#1100
b100 !
b100 )
b100 (
b1110 #
b1110 '
b1110 %
#1110
b101 !
b101 )
b101 (
b1111 #
b1111 '
b1111 %
#1120
b111 !
b111 )
b0 #
b0 '
b111 (
b111 "
b111 &
b111 $
b0 %
#1130
b1000 !
b1000 )
b1000 (
b1 #
b1 '
b1 %
#1140
b1001 !
b1001 )
b1001 (
b10 #
b10 '
b10 %
#1150
b0 !
b0 )
b1010 (
b11 #
b11 '
b11 %
#1160
b1 !
b1 )
b1011 (
b100 #
b100 '
b100 %
#1170
b10 !
b10 )
b1100 (
b101 #
b101 '
b101 %
#1180
b11 !
b11 )
b1101 (
b110 #
b110 '
b110 %
#1190
b100 !
b100 )
b1110 (
b111 #
b111 '
b111 %
#1200
b101 !
b101 )
b1111 (
b1000 #
b1000 '
b1000 %
#1210
b0 !
b0 )
b0 (
b1001 #
b1001 '
b1001 %
#1220
b1 !
b1 )
b1 (
b1010 #
b1010 '
b1010 %
#1230
b10 !
b10 )
b10 (
b1011 #
b1011 '
b1011 %
#1240
b11 !
b11 )
b11 (
b1100 #
b1100 '
b1100 %
#1250
b100 !
b100 )
b100 (
b1101 #
b1101 '
b1101 %
#1260
b101 !
b101 )
b101 (
b1110 #
b1110 '
b1110 %
#1270
b110 !
b110 )
b110 (
b1111 #
b1111 '
b1111 %
#1280
b1000 !
b1000 )
b0 #
b0 '
b1000 (
b1000 "
b1000 &
b1000 $
b0 %
#1290
b1001 !
b1001 )
b1001 (
b1 #
b1 '
b1 %
#1300
b0 !
b0 )
b1010 (
b10 #
b10 '
b10 %
#1310
b1 !
b1 )
b1011 (
b11 #
b11 '
b11 %
#1320
b10 !
b10 )
b1100 (
b100 #
b100 '
b100 %
#1330
b11 !
b11 )
b1101 (
b101 #
b101 '
b101 %
#1340
b100 !
b100 )
b1110 (
b110 #
b110 '
b110 %
#1350
b101 !
b101 )
b1111 (
b111 #
b111 '
b111 %
#1360
b0 !
b0 )
b0 (
b1000 #
b1000 '
b1000 %
#1370
b1 !
b1 )
b1 (
b1001 #
b1001 '
b1001 %
#1380
b10 !
b10 )
b10 (
b1010 #
b1010 '
b1010 %
#1390
b11 !
b11 )
b11 (
b1011 #
b1011 '
b1011 %
#1400
b100 !
b100 )
b100 (
b1100 #
b1100 '
b1100 %
#1410
b101 !
b101 )
b101 (
b1101 #
b1101 '
b1101 %
#1420
b110 !
b110 )
b110 (
b1110 #
b1110 '
b1110 %
#1430
b111 !
b111 )
b111 (
b1111 #
b1111 '
b1111 %
#1440
b1001 !
b1001 )
b0 #
b0 '
b1001 (
b1001 "
b1001 &
b1001 $
b0 %
#1450
b0 !
b0 )
b1010 (
b1 #
b1 '
b1 %
#1460
b1 !
b1 )
b1011 (
b10 #
b10 '
b10 %
#1470
b10 !
b10 )
b1100 (
b11 #
b11 '
b11 %
#1480
b11 !
b11 )
b1101 (
b100 #
b100 '
b100 %
#1490
b100 !
b100 )
b1110 (
b101 #
b101 '
b101 %
#1500
b101 !
b101 )
b1111 (
b110 #
b110 '
b110 %
#1510
b0 !
b0 )
b0 (
b111 #
b111 '
b111 %
#1520
b1 !
b1 )
b1 (
b1000 #
b1000 '
b1000 %
#1530
b10 !
b10 )
b10 (
b1001 #
b1001 '
b1001 %
#1540
b11 !
b11 )
b11 (
b1010 #
b1010 '
b1010 %
#1550
b100 !
b100 )
b100 (
b1011 #
b1011 '
b1011 %
#1560
b101 !
b101 )
b101 (
b1100 #
b1100 '
b1100 %
#1570
b110 !
b110 )
b110 (
b1101 #
b1101 '
b1101 %
#1580
b111 !
b111 )
b111 (
b1110 #
b1110 '
b1110 %
#1590
b1000 !
b1000 )
b1000 (
b1111 #
b1111 '
b1111 %
#1600
b0 !
b0 )
b0 #
b0 '
b1010 (
b1010 "
b1010 &
b1010 $
b0 %
#1610
b1 !
b1 )
b1011 (
b1 #
b1 '
b1 %
#1620
b10 !
b10 )
b1100 (
b10 #
b10 '
b10 %
#1630
b11 !
b11 )
b1101 (
b11 #
b11 '
b11 %
#1640
b100 !
b100 )
b1110 (
b100 #
b100 '
b100 %
#1650
b101 !
b101 )
b1111 (
b101 #
b101 '
b101 %
#1660
b0 !
b0 )
b0 (
b110 #
b110 '
b110 %
#1670
b1 !
b1 )
b1 (
b111 #
b111 '
b111 %
#1680
b10 !
b10 )
b10 (
b1000 #
b1000 '
b1000 %
#1690
b11 !
b11 )
b11 (
b1001 #
b1001 '
b1001 %
#1700
b100 !
b100 )
b100 (
b1010 #
b1010 '
b1010 %
#1710
b101 !
b101 )
b101 (
b1011 #
b1011 '
b1011 %
#1720
b110 !
b110 )
b110 (
b1100 #
b1100 '
b1100 %
#1730
b111 !
b111 )
b111 (
b1101 #
b1101 '
b1101 %
#1740
b1000 !
b1000 )
b1000 (
b1110 #
b1110 '
b1110 %
#1750
b1001 !
b1001 )
b1001 (
b1111 #
b1111 '
b1111 %
#1760
b1 !
b1 )
b0 #
b0 '
b1011 (
b1011 "
b1011 &
b1011 $
b0 %
#1770
b10 !
b10 )
b1100 (
b1 #
b1 '
b1 %
#1780
b11 !
b11 )
b1101 (
b10 #
b10 '
b10 %
#1790
b100 !
b100 )
b1110 (
b11 #
b11 '
b11 %
#1800
b101 !
b101 )
b1111 (
b100 #
b100 '
b100 %
#1810
b0 !
b0 )
b0 (
b101 #
b101 '
b101 %
#1820
b1 !
b1 )
b1 (
b110 #
b110 '
b110 %
#1830
b10 !
b10 )
b10 (
b111 #
b111 '
b111 %
#1840
b11 !
b11 )
b11 (
b1000 #
b1000 '
b1000 %
#1850
b100 !
b100 )
b100 (
b1001 #
b1001 '
b1001 %
#1860
b101 !
b101 )
b101 (
b1010 #
b1010 '
b1010 %
#1870
b110 !
b110 )
b110 (
b1011 #
b1011 '
b1011 %
#1880
b111 !
b111 )
b111 (
b1100 #
b1100 '
b1100 %
#1890
b1000 !
b1000 )
b1000 (
b1101 #
b1101 '
b1101 %
#1900
b1001 !
b1001 )
b1001 (
b1110 #
b1110 '
b1110 %
#1910
b0 !
b0 )
b1010 (
b1111 #
b1111 '
b1111 %
#1920
b10 !
b10 )
b0 #
b0 '
b1100 (
b1100 "
b1100 &
b1100 $
b0 %
#1930
b11 !
b11 )
b1101 (
b1 #
b1 '
b1 %
#1940
b100 !
b100 )
b1110 (
b10 #
b10 '
b10 %
#1950
b101 !
b101 )
b1111 (
b11 #
b11 '
b11 %
#1960
b0 !
b0 )
b0 (
b100 #
b100 '
b100 %
#1970
b1 !
b1 )
b1 (
b101 #
b101 '
b101 %
#1980
b10 !
b10 )
b10 (
b110 #
b110 '
b110 %
#1990
b11 !
b11 )
b11 (
b111 #
b111 '
b111 %
#2000
b100 !
b100 )
b100 (
b1000 #
b1000 '
b1000 %
#2010
b101 !
b101 )
b101 (
b1001 #
b1001 '
b1001 %
#2020
b110 !
b110 )
b110 (
b1010 #
b1010 '
b1010 %
#2030
b111 !
b111 )
b111 (
b1011 #
b1011 '
b1011 %
#2040
b1000 !
b1000 )
b1000 (
b1100 #
b1100 '
b1100 %
#2050
b1001 !
b1001 )
b1001 (
b1101 #
b1101 '
b1101 %
#2060
b0 !
b0 )
b1010 (
b1110 #
b1110 '
b1110 %
#2070
b1 !
b1 )
b1011 (
b1111 #
b1111 '
b1111 %
#2080
b11 !
b11 )
b0 #
b0 '
b1101 (
b1101 "
b1101 &
b1101 $
b0 %
#2090
b100 !
b100 )
b1110 (
b1 #
b1 '
b1 %
#2100
b101 !
b101 )
b1111 (
b10 #
b10 '
b10 %
#2110
b0 !
b0 )
b0 (
b11 #
b11 '
b11 %
#2120
b1 !
b1 )
b1 (
b100 #
b100 '
b100 %
#2130
b10 !
b10 )
b10 (
b101 #
b101 '
b101 %
#2140
b11 !
b11 )
b11 (
b110 #
b110 '
b110 %
#2150
b100 !
b100 )
b100 (
b111 #
b111 '
b111 %
#2160
b101 !
b101 )
b101 (
b1000 #
b1000 '
b1000 %
#2170
b110 !
b110 )
b110 (
b1001 #
b1001 '
b1001 %
#2180
b111 !
b111 )
b111 (
b1010 #
b1010 '
b1010 %
#2190
b1000 !
b1000 )
b1000 (
b1011 #
b1011 '
b1011 %
#2200
b1001 !
b1001 )
b1001 (
b1100 #
b1100 '
b1100 %
#2210
b0 !
b0 )
b1010 (
b1101 #
b1101 '
b1101 %
#2220
b1 !
b1 )
b1011 (
b1110 #
b1110 '
b1110 %
#2230
b10 !
b10 )
b1100 (
b1111 #
b1111 '
b1111 %
#2240
b100 !
b100 )
b0 #
b0 '
b1110 (
b1110 "
b1110 &
b1110 $
b0 %
#2250
b101 !
b101 )
b1111 (
b1 #
b1 '
b1 %
#2260
b0 !
b0 )
b0 (
b10 #
b10 '
b10 %
#2270
b1 !
b1 )
b1 (
b11 #
b11 '
b11 %
#2280
b10 !
b10 )
b10 (
b100 #
b100 '
b100 %
#2290
b11 !
b11 )
b11 (
b101 #
b101 '
b101 %
#2300
b100 !
b100 )
b100 (
b110 #
b110 '
b110 %
#2310
b101 !
b101 )
b101 (
b111 #
b111 '
b111 %
#2320
b110 !
b110 )
b110 (
b1000 #
b1000 '
b1000 %
#2330
b111 !
b111 )
b111 (
b1001 #
b1001 '
b1001 %
#2340
b1000 !
b1000 )
b1000 (
b1010 #
b1010 '
b1010 %
#2350
b1001 !
b1001 )
b1001 (
b1011 #
b1011 '
b1011 %
#2360
b0 !
b0 )
b1010 (
b1100 #
b1100 '
b1100 %
#2370
b1 !
b1 )
b1011 (
b1101 #
b1101 '
b1101 %
#2380
b10 !
b10 )
b1100 (
b1110 #
b1110 '
b1110 %
#2390
b11 !
b11 )
b1101 (
b1111 #
b1111 '
b1111 %
#2400
b101 !
b101 )
b0 #
b0 '
b1111 (
b1111 "
b1111 &
b1111 $
b0 %
#2410
b0 !
b0 )
b0 (
b1 #
b1 '
b1 %
#2420
b1 !
b1 )
b1 (
b10 #
b10 '
b10 %
#2430
b10 !
b10 )
b10 (
b11 #
b11 '
b11 %
#2440
b11 !
b11 )
b11 (
b100 #
b100 '
b100 %
#2450
b100 !
b100 )
b100 (
b101 #
b101 '
b101 %
#2460
b101 !
b101 )
b101 (
b110 #
b110 '
b110 %
#2470
b110 !
b110 )
b110 (
b111 #
b111 '
b111 %
#2480
b111 !
b111 )
b111 (
b1000 #
b1000 '
b1000 %
#2490
b1000 !
b1000 )
b1000 (
b1001 #
b1001 '
b1001 %
#2500
b1001 !
b1001 )
b1001 (
b1010 #
b1010 '
b1010 %
#2510
b0 !
b0 )
b1010 (
b1011 #
b1011 '
b1011 %
#2520
b1 !
b1 )
b1011 (
b1100 #
b1100 '
b1100 %
#2530
b10 !
b10 )
b1100 (
b1101 #
b1101 '
b1101 %
#2540
b11 !
b11 )
b1101 (
b1110 #
b1110 '
b1110 %
#2550
b100 !
b100 )
b1110 (
b1111 #
b1111 '
b1111 %
#2560
b10000 $
b10000 %
